probatus/__init__.py
probatus/feature_elimination/__init__.py
probatus/feature_elimination/early_stopping_feature_elimination.py
probatus/feature_elimination/feature_elimination.py
probatus/interpret/__init__.py
probatus/interpret/model_interpret.py
probatus/interpret/shap_dependence.py
probatus/sample_similarity/__init__.py
probatus/sample_similarity/resemblance_model.py
probatus/utils/__init__.py
probatus/utils/_utils.py
probatus/utils/arrayfuncs.py
probatus/utils/base_class_interface.py
probatus/utils/exceptions.py
probatus/utils/scoring.py
probatus/utils/shap_helpers.py
probatus-3.1.3.dist-info/licenses/LICENCE
tests/docs/__init__.py
tests/docs/test_docstring.py
tests/docs/test_notebooks.py
tests/feature_elimination/test_feature_elimination.py
tests/interpret/__init__.py
tests/interpret/test_model_interpret.py
tests/interpret/test_shap_dependence.py
tests/sample_similarity/__init__.py
tests/sample_similarity/test_resemblance_model.py
tests/utils/__init__.py
tests/utils/test_base_class.py
tests/utils/test_utils_array_funcs.py
probatus-3.1.3.dist-info/METADATA
probatus-3.1.3.dist-info/WHEEL
probatus-3.1.3.dist-info/top_level.txt
probatus-3.1.3.dist-info/RECORD
