Metadata-Version: 2.4
Name: probatus
Version: 3.1.3
Summary: Validation of regression & classifiers and data used to develop them
Author-email: "ING Bank N.V." <reinier.koops@ing.com>
License: Copyright (c) ING Bank N.V.
Project-URL: Homepage, https://ing-bank.github.io/probatus/
Project-URL: Documentation, https://ing-bank.github.io/probatus/api/feature_elimination.html
Project-URL: Repository, https://github.com/ing-bank/probatus.git
Project-URL: Changelog, https://github.com/ing-bank/probatus/blob/main/CHANGELOG.md
Classifier: Intended Audience :: Developers
Classifier: Intended Audience :: Science/Research
Classifier: Programming Language :: Python :: 3
Classifier: Programming Language :: Python :: 3.9
Classifier: Programming Language :: Python :: 3.10
Classifier: Programming Language :: Python :: 3.11
Classifier: Programming Language :: Python :: 3.12
Classifier: Topic :: Scientific/Engineering
Classifier: Topic :: Scientific/Engineering :: Artificial Intelligence
Classifier: License :: OSI Approved :: MIT License
Classifier: Operating System :: OS Independent
Requires-Python: >=3.9
License-File: LICENCE
Requires-Dist: scikit-learn>=0.22.2
Requires-Dist: pandas>=1.0.0
Requires-Dist: matplotlib>=3.1.1
Requires-Dist: joblib>=0.13.2
Requires-Dist: shap>=0.43.0
Requires-Dist: numpy<2.0.0,>=1.23.2
Requires-Dist: numba>=0.57.0
Requires-Dist: loguru>=0.7.2
Provides-Extra: dev
Requires-Dist: black>=19.10b0; extra == "dev"
Requires-Dist: mypy>=0.770; extra == "dev"
Requires-Dist: pytest>=6.0.0; extra == "dev"
Requires-Dist: pytest-cov>=2.10.0; extra == "dev"
Requires-Dist: pyflakes; extra == "dev"
Requires-Dist: joblib>=0.13.2; extra == "dev"
Requires-Dist: jupyter>=1.0.0; extra == "dev"
Requires-Dist: nbconvert>=6.0.7; extra == "dev"
Requires-Dist: pre-commit>=2.7.1; extra == "dev"
Requires-Dist: isort>=5.12.0; extra == "dev"
Requires-Dist: codespell>=2.2.4; extra == "dev"
Requires-Dist: ruff>=0.2.2; extra == "dev"
Requires-Dist: lightgbm>=3.3.0; extra == "dev"
Requires-Dist: catboost>=1.2; extra == "dev"
Requires-Dist: xgboost>=1.5.0; extra == "dev"
Provides-Extra: docs
Requires-Dist: mkdocs>=1.5.3; extra == "docs"
Requires-Dist: mkdocs-jupyter>=0.24.3; extra == "docs"
Requires-Dist: mkdocs-material>=9.5.13; extra == "docs"
Requires-Dist: mkdocstrings>=0.24.1; extra == "docs"
Requires-Dist: mkdocstrings-python>=1.8.0; extra == "docs"
Provides-Extra: all
Requires-Dist: probatus[dev,docs]; extra == "all"
Dynamic: license-file
